zjcaod/__init__.py
zjcaod/http.py
zjcaod-0.0.2.dist-info/LICENSE
zjcaod-0.0.2.dist-info/METADATA
zjcaod-0.0.2.dist-info/WHEEL
zjcaod-0.0.2.dist-info/top_level.txt
zjcaod-0.0.2.dist-info/RECORD
