Metadata-Version: 2.1
Name: zjcaod
Version: 0.0.2
Summary: zjcaod tools
Home-page: UNKNOWN
Author: zjcaod
Author-email: 1352514347@qq.com
License: UNKNOWN
Platform: UNKNOWN
Requires-Python: >=3.6
